[
  {
    "id": "xaodvvu",
    "title": "ساحر أفالون(بالعربية)",
    "thumbnail": "https://s2.dmcdn.net/v/cUsAg1gKiXiH9Pej9",
    "m3u8Url": "https://cdndirector.dailymotion.com/cdn/manifest/video/xaodvvu.m3u8?sec=f5lfc6xtduVXYN5ylmcrB8-__rtRHAuB49xZvhqUjkyR-TmCFSRckSZAVRWAsjx_GLlSXKRvJpjICnqd6q7Cfw&dmTs=356548&dmV1st=3913D66CABB2B719BFFC5067ADC24F95",
    "embedUrl": "https://www.dailymotion.com/embed/video/xaodvvu",
    "duration": 4112,
    "views": 9178,
    "uploadedAt": "2026-07-11T15:54:41.000Z",
    "timestamp": 1783785281
  },
  {
    "id": "xaodvvq",
    "title": "ساحة المبارزة  أستدعي الآلهة لإنقاذ العالم",
    "thumbnail": "https://s2.dmcdn.net/v/cUsAc1gKiZpkKZ5lY",
    "m3u8Url": "https://cdndirector.dailymotion.com/cdn/manifest/video/xaodvvq.m3u8?sec=U__z_LRRMzY2VtYBfKkYCnE8KYlDBJ48wtEScLz6GKIwa5tUXxjk6pD6rV6N3UFspdodXaxhau-tD0AZQw_wHA&dmTs=824276&dmV1st=051E70D2DE9A6F0D5EB91BBCEA6167C3",
    "embedUrl": "https://www.dailymotion.com/embed/video/xaodvvq",
    "duration": 4779,
    "views": 40803,
    "uploadedAt": "2026-07-11T15:54:28.000Z",
    "timestamp": 1783785268
  },
  {
    "id": "xaodjli",
    "title": "حُماة العاطفة بين عالمين",
    "thumbnail": "https://s2.dmcdn.net/v/cUoHs1gKjGt0JGDne",
    "m3u8Url": "https://cdndirector.dailymotion.com/cdn/manifest/video/xaodjli.m3u8?sec=TLoy5zOXcsjTxrcS2hFM9sUdCFHunuBgcRAW4Een0VafaHUlSMfnZoFZuE4ZMpdVYtyuPnD-5mAxrlmBN3zq_A&dmTs=217538&dmV1st=2A63EDE2A2D920B0FF1A2850AF332F83",
    "embedUrl": "https://www.dailymotion.com/embed/video/xaodjli",
    "duration": 7911,
    "views": 18155,
    "uploadedAt": "2026-07-11T11:01:25.000Z",
    "timestamp": 1783767685
  },
  {
    "id": "xaodjlq",
    "title": "وفاء الثعبان",
    "thumbnail": "https://s2.dmcdn.net/v/cUoH-1gKiWyADds3e",
    "m3u8Url": "https://cdndirector.dailymotion.com/cdn/manifest/video/xaodjlq.m3u8?sec=lYTtHYml4LQsP6j8NZAS-f3bbdEAVQEo7mkAhiL2nJNgpYbsRNup2y7Yymi59kNkCBxtf3ptp76wEZ5gMt7cMw&dmTs=68500&dmV1st=E8765B1FED9370A7EC17D83E779479BA",
    "embedUrl": "https://www.dailymotion.com/embed/video/xaodjlq",
    "duration": 7188,
    "views": 34554,
    "uploadedAt": "2026-07-11T10:56:33.000Z",
    "timestamp": 1783767393
  },
  {
    "id": "xaodjle",
    "title": "[مدبلج]عودة الصفاء بعد العاصفة",
    "thumbnail": "https://s2.dmcdn.net/v/cUoHo1gKn-3SrCysq",
    "m3u8Url": "https://cdndirector.dailymotion.com/cdn/manifest/video/xaodjle.m3u8?sec=oMii7kjvxFgUFKB2so73uXMcyAeKCodbe30uLK-srQGIstZwMpuiY0ClcBs_ihT88hp8OsHwa_6NCBEKSka4og&dmTs=114469&dmV1st=70BE0A74A6452B5ED667A3D408909A13",
    "embedUrl": "https://www.dailymotion.com/embed/video/xaodjle",
    "duration": 5510,
    "views": 5609,
    "uploadedAt": "2026-07-11T10:52:16.000Z",
    "timestamp": 1783767136
  },
  {
    "id": "xaodjlu",
    "title": "صفعة قبل الفرح",
    "thumbnail": "https://s1.dmcdn.net/v/cUoI21gKhtmEwbNdR",
    "m3u8Url": "https://cdndirector.dailymotion.com/cdn/manifest/video/xaodjlu.m3u8?sec=D18C8pIkyeyV7sENukkS4JAuMSk9R5sQwTM5-bsfgF6G8Po_7tI_FHaeAVol4PawIkgzmwiBEoEtpjhPlMx-Uw&dmTs=8699&dmV1st=2920E72E72766ADC25458A0C8047CE30",
    "embedUrl": "https://www.dailymotion.com/embed/video/xaodjlu",
    "duration": 1494,
    "views": 27146,
    "uploadedAt": "2026-07-11T10:44:24.000Z",
    "timestamp": 1783766664
  },
  {
    "id": "xaodjlm",
    "title": "قلادة الصدق القاتلة",
    "thumbnail": "https://s2.dmcdn.net/v/cUoHw1gKhy8MlTrhD",
    "m3u8Url": "https://cdndirector.dailymotion.com/cdn/manifest/video/xaodjlm.m3u8?sec=HCqFOq_2N6lDhZEKD8iBCDPbYKuZ0ANpUSZnRW39jXXYlOSQgR6oP_HZ7fzhsigRKKiX8fquwqfRQCiRO1L9Fg&dmTs=290051&dmV1st=AE3F286041F1A36AB6F33A86043F0074",
    "embedUrl": "https://www.dailymotion.com/embed/video/xaodjlm",
    "duration": 2136,
    "views": 17388,
    "uploadedAt": "2026-07-11T10:44:16.000Z",
    "timestamp": 1783766656
  },
  {
    "id": "xaod5m6",
    "title": "بعد الفوات، لا عودة",
    "thumbnail": "https://s2.dmcdn.net/v/cUjsk1gKy1G8JAuOP",
    "m3u8Url": "https://cdndirector.dailymotion.com/cdn/manifest/video/xaod5m6.m3u8?sec=SXLFKZNNGD2Ybsmj3We-7GSA2jWnuiQ8SbSahagqbuHq6Vq3n1iYaPDMx06MZQqdkyrK-MZkC4DueHfAR211gQ&dmTs=772141&dmV1st=8C0EB32C9588FC396EF68C79CE679098",
    "embedUrl": "https://www.dailymotion.com/embed/video/xaod5m6",
    "duration": 7622,
    "views": 7867,
    "uploadedAt": "2026-07-11T09:54:15.000Z",
    "timestamp": 1783763655
  },
  {
    "id": "xao5k9m",
    "title": "مشاهدة مسلسل ساحر أفالون مدبلج كامل",
    "thumbnail": "https://s2.dmcdn.net/v/cTNNQ1gKQMTkdwWCo",
    "m3u8Url": "https://cdndirector.dailymotion.com/cdn/manifest/video/xao5k9m.m3u8?sec=jb1QpgVVW41m3_Acv95HTJ1TaWfcFfs-3fpDsVx9K1JLD7GQBYWmx98ZKs2-EBuz3tlG0AtYRiSoXJvg_yzgVg&dmTs=381987&dmV1st=646BC9C8E5F804858E04A10509259781",
    "embedUrl": "https://www.dailymotion.com/embed/video/xao5k9m",
    "duration": 4107,
    "views": 7609,
    "uploadedAt": "2026-07-10T15:08:20.000Z",
    "timestamp": 1783696100
  },
  {
    "id": "xao27ga",
    "title": "مسلسل العائلة التي دفعتني للموت مدبلج كامل جميع الحلقات بجودة عالية",
    "thumbnail": "https://s2.dmcdn.net/v/cSn8w1gKOdHKtG3Si",
    "m3u8Url": "https://cdndirector.dailymotion.com/cdn/manifest/video/xao27ga.m3u8?sec=gysqCkiykzndnLw_IvWXlcnex3yPH949jVF88FRK0t7-ahno_ebpTQw_tKXFpuw3BkCUYuJF7GYBjegdGEOKSw&dmTs=287565&dmV1st=3C9FC9E21839D6E0A75132EA3A6979CC",
    "embedUrl": "https://www.dailymotion.com/embed/video/xao27ga",
    "duration": 2383,
    "views": 36686,
    "uploadedAt": "2026-07-10T11:35:05.000Z",
    "timestamp": 1783683305
  },
  {
    "id": "xansujm",
    "title": "خطيئة الأب",
    "thumbnail": "https://s2.dmcdn.net/v/cR6YY1gKRqUIuP65k",
    "m3u8Url": "https://cdndirector.dailymotion.com/cdn/manifest/video/xansujm.m3u8?sec=rYRp8KhYYnui2m85RY7fJXDRJjExq0UMe47O0YRWoLziwgjbH2-_gDrQXI8uOS68a-YK2TPqy7_VvbIrOEYM_Q&dmTs=829422&dmV1st=A75F597E5A141C52019E0BA9030801EC",
    "embedUrl": "https://www.dailymotion.com/embed/video/xansujm",
    "duration": 2187,
    "views": 35705,
    "uploadedAt": "2026-07-10T01:45:10.000Z",
    "timestamp": 1783647910
  },
  {
    "id": "xansuji",
    "title": "عروس التنين الشرير البديلة",
    "thumbnail": "https://s2.dmcdn.net/v/cR6YU1gKgaT8eyjtB",
    "m3u8Url": "https://cdndirector.dailymotion.com/cdn/manifest/video/xansuji.m3u8?sec=IsjWrxWM7H7EwPaSOoWWYDac0MzTUAGeD_MTG2OXndUnOS7le2JGJpD5RelXZcrEV29-hYy4vmWpllDYJWmRww&dmTs=106882&dmV1st=92945A287A0D55BA15748D808A3A4BE6",
    "embedUrl": "https://www.dailymotion.com/embed/video/xansuji",
    "duration": 4059,
    "views": 31384,
    "uploadedAt": "2026-07-10T01:44:57.000Z",
    "timestamp": 1783647897
  },
  {
    "id": "xansujq",
    "title": "الجنيّ المتعاقد",
    "thumbnail": "https://s2.dmcdn.net/v/cR6Yc1gKHtgxGLfzh",
    "m3u8Url": "https://cdndirector.dailymotion.com/cdn/manifest/video/xansujq.m3u8?sec=znxxDExQE5TM6i684xhfdl1FNPmR8y8T4JVnCMQ3K3vSuqdnsGlx2m148FW91RJaKc97Zcq1scL8h94LVyvKWQ&dmTs=860420&dmV1st=F0CD139FB52849A4D2D6302AB9C3B1D6",
    "embedUrl": "https://www.dailymotion.com/embed/video/xansujq",
    "duration": 6175,
    "views": 47474,
    "uploadedAt": "2026-07-10T01:44:45.000Z",
    "timestamp": 1783647885
  },
  {
    "id": "xansuka",
    "title": "صعود ملك الكونغ فو",
    "thumbnail": "https://s2.dmcdn.net/v/cR6Yw1gKHqgxRW8Ww",
    "m3u8Url": "https://cdndirector.dailymotion.com/cdn/manifest/video/xansuka.m3u8?sec=UTMAi1DIYavv5bgLQp2pmzv8a09EKLDL0Co115EnFUprTMKzVI7V49gCDoYUVSrGYiAYNr_-dfEFhtT9cwWH5Q&dmTs=438692&dmV1st=2E8ED90075A79A6C8017B28F80BFDB9F",
    "embedUrl": "https://www.dailymotion.com/embed/video/xansuka",
    "duration": 7065,
    "views": 27078,
    "uploadedAt": "2026-07-10T01:44:27.000Z",
    "timestamp": 1783647867
  },
  {
    "id": "xansuju",
    "title": "صحوة التنين التنين الكامن بداخلي استيقظ!",
    "thumbnail": "https://s2.dmcdn.net/v/cR6Yg1gKHunFc2L06",
    "m3u8Url": "https://cdndirector.dailymotion.com/cdn/manifest/video/xansuju.m3u8?sec=bAqc4BG3RWwejl76CuXG0XOShoyWgIP8R6ZkejMi90jzswiiTcZhJt0euIK0uHHz1oWYsUvnLh1wrl-6Ignkdg&dmTs=464426&dmV1st=0284B6C0A356D00033D507414836E86D",
    "embedUrl": "https://www.dailymotion.com/embed/video/xansuju",
    "duration": 8075,
    "views": 22385,
    "uploadedAt": "2026-07-10T01:44:13.000Z",
    "timestamp": 1783647853
  },
  {
    "id": "xansujy",
    "title": "أسطورة القزم في كرة السلة",
    "thumbnail": "https://s2.dmcdn.net/v/cR6Yk1gKHuD-qromO",
    "m3u8Url": "https://cdndirector.dailymotion.com/cdn/manifest/video/xansujy.m3u8?sec=1zc3UZZPQP7yQOvAfmJzcMTOxq8B4E5LqeQ7tQgH4wNRg1LOQdWZn7rseXhUCXSCDJQC0MA-DQjVb_6YJCYdTg&dmTs=954592&dmV1st=78E6B038AB30B54C19916DC92BB94473",
    "embedUrl": "https://www.dailymotion.com/embed/video/xansujy",
    "duration": 7520,
    "views": 24159,
    "uploadedAt": "2026-07-10T01:43:26.000Z",
    "timestamp": 1783647806
  },
  {
    "id": "xan1hiu",
    "title": "حبٌّ مع شروق الفجر مدبلج - مشاهدة مسلسل كامل",
    "thumbnail": "https://s1.dmcdn.net/v/cMEts1gKNjQWhtOjM",
    "m3u8Url": "https://cdndirector.dailymotion.com/cdn/manifest/video/xan1hiu.m3u8?sec=eCKa3IxpQghgtupvFxAIv7T6tfJ90cIxDE-zGTliDYykthg1x-PrzRr32aqbhwVFjqsf7bbrfzLn6cimfaHwag&dmTs=826723&dmV1st=6E993751E13BCBD4630668A72DD3F42F",
    "embedUrl": "https://www.dailymotion.com/embed/video/xan1hiu",
    "duration": 6404,
    "views": 32270,
    "uploadedAt": "2026-07-08T19:47:22.000Z",
    "timestamp": 1783540042
  },
  {
    "id": "xamnr02",
    "title": "قطعة برجر مزدوجة",
    "thumbnail": "https://s1.dmcdn.net/v/cJoPo1gJveejTo9Bg",
    "m3u8Url": "https://cdndirector.dailymotion.com/cdn/manifest/video/xamnr02.m3u8?sec=ER8KQ2hh8Go9smAMEMDuvgco4MhHzNbZKGd77UPZXXTS5ezDu54nLHNxy3_sZ98hfGPoZRLydpLJwk4-H6x1Jw&dmTs=204886&dmV1st=70514A3975FA66D825822AA774A5D7FD",
    "embedUrl": "https://www.dailymotion.com/embed/video/xamnr02",
    "duration": 2011,
    "views": 32632,
    "uploadedAt": "2026-07-08T05:00:55.000Z",
    "timestamp": 1783486855
  },
  {
    "id": "xamnqzu",
    "title": "حصني المتحرك في النهاية",
    "thumbnail": "https://s2.dmcdn.net/v/cJoPg1gJjOkNmrqU7",
    "m3u8Url": "https://cdndirector.dailymotion.com/cdn/manifest/video/xamnqzu.m3u8?sec=brJQlAC1HlWvFXMdZ3hawBU8pjd1fmC4wauCK9duxcZ-qnZjobcoYgCUuLtHcF4x30ZvTVviYLP3ov1KIKdhfA&dmTs=83220&dmV1st=A247A0F24A5DA2DB8704C6026EF070CB",
    "embedUrl": "https://www.dailymotion.com/embed/video/xamnqzu",
    "duration": 6024,
    "views": 36909,
    "uploadedAt": "2026-07-08T05:00:50.000Z",
    "timestamp": 1783486850
  },
  {
    "id": "xamnr0a",
    "title": "العودة المهيبة",
    "thumbnail": "https://s2.dmcdn.net/v/cJoPw1gJjKbn8wytv",
    "m3u8Url": "https://cdndirector.dailymotion.com/cdn/manifest/video/xamnr0a.m3u8?sec=AazJrBt30qpEWE65r2-lv0lB4gUvs_3sneAgTwBnCzX8pBtQj2nR13CoQJ_F6IonwiE80YtzzQQT9_HWmetp5Q&dmTs=795563&dmV1st=8A4794BDD22E4E6F105EF32A3D6302BE",
    "embedUrl": "https://www.dailymotion.com/embed/video/xamnr0a",
    "duration": 5077,
    "views": 13908,
    "uploadedAt": "2026-07-08T05:00:44.000Z",
    "timestamp": 1783486844
  },
  {
    "id": "xamnr0q",
    "title": "العاصفة  آخر درع للبشرية",
    "thumbnail": "https://s1.dmcdn.net/v/cJoQA1gJs9PsDM7z8",
    "m3u8Url": "https://cdndirector.dailymotion.com/cdn/manifest/video/xamnr0q.m3u8?sec=x77EN-qBmZQ9t8p8h1eVCYIL-897DfkONi9dJOa2oztmLhMJGKh3J6Muu2BqZBDFE952KPZJ0D3iKEacnOSx9A&dmTs=234194&dmV1st=0F448346596450B794B5A718499BE644",
    "embedUrl": "https://www.dailymotion.com/embed/video/xamnr0q",
    "duration": 6497,
    "views": 44158,
    "uploadedAt": "2026-07-08T05:00:32.000Z",
    "timestamp": 1783486832
  },
  {
    "id": "xamnr06",
    "title": "صحوة العبقري",
    "thumbnail": "https://s2.dmcdn.net/v/cJoPs1gJl69puipzg",
    "m3u8Url": "https://cdndirector.dailymotion.com/cdn/manifest/video/xamnr06.m3u8?sec=2NyYDNRz37a3SxgcG0xMY5JQWWar_oT0orJd5jA4fHiAesfuMwhbn_rBR-oSMxL0KVF7kbyu5zUmAb6qE7lJ1A&dmTs=561081&dmV1st=A87303896AFD379527B17883C23D3E6F",
    "embedUrl": "https://www.dailymotion.com/embed/video/xamnr06",
    "duration": 9424,
    "views": 23102,
    "uploadedAt": "2026-07-08T05:00:22.000Z",
    "timestamp": 1783486822
  },
  {
    "id": "xamnulm",
    "title": "سقوط نجم الظهيرة (مدبلج)",
    "thumbnail": "https://s1.dmcdn.net/v/cJpYg1gKZwmHsb1f7",
    "m3u8Url": "https://cdndirector.dailymotion.com/cdn/manifest/video/xamnulm.m3u8?sec=CU3b3aXWpBWdxrATRHm5TRYMoCaiycaNS_IjIkRQIGRJ1q_3yRr9SJwciHA9xcABlsml8wLvKKai95O6Su76BQ&dmTs=214236&dmV1st=11CEA7D9CCC4E5B05CCD058458830A21",
    "embedUrl": "https://www.dailymotion.com/embed/video/xamnulm",
    "duration": 8337,
    "views": 29525,
    "uploadedAt": "2026-07-08T05:00:17.000Z",
    "timestamp": 1783486817
  },
  {
    "id": "xamnuli",
    "title": "سقوط نجم الظهيرة",
    "thumbnail": "https://s1.dmcdn.net/v/cJpYc1gKZzGwvYYd9",
    "m3u8Url": "https://cdndirector.dailymotion.com/cdn/manifest/video/xamnuli.m3u8?sec=9AVoSK911iuUPDTmxp-1pZ7t5--NV_Pkd7wFHbBYR5QFGJByF0_yxS7uhOxTTPNO7OvcnzrTHUPWKLO1mZCjbA&dmTs=935206&dmV1st=89A3D84D0DD5A6C2D73F854BA4122FDB",
    "embedUrl": "https://www.dailymotion.com/embed/video/xamnuli",
    "duration": 8336,
    "views": 38187,
    "uploadedAt": "2026-07-08T05:00:11.000Z",
    "timestamp": 1783486811
  },
  {
    "id": "xamnule",
    "title": "بعد الفوات، لا عودة",
    "thumbnail": "https://s2.dmcdn.net/v/cJpYY1gJq3KbRO326",
    "m3u8Url": "https://cdndirector.dailymotion.com/cdn/manifest/video/xamnule.m3u8?sec=f8ekm8NLDTIy-wX8l-hRPeu1spiaB9v7CUh5qbHLtawdHuRFRJfzCzksL_aYjYr4hPZUQSfu8xb8xUiqbak0cw&dmTs=940344&dmV1st=1B719C5204D8801A79B075550C8382A7",
    "embedUrl": "https://www.dailymotion.com/embed/video/xamnule",
    "duration": 7618,
    "views": 36558,
    "uploadedAt": "2026-07-08T05:00:04.000Z",
    "timestamp": 1783486804
  },
  {
    "id": "xamnulq",
    "title": "الحب مرة أخرى",
    "thumbnail": "https://s1.dmcdn.net/v/cJpYk1gJTazHRNVzW",
    "m3u8Url": "https://cdndirector.dailymotion.com/cdn/manifest/video/xamnulq.m3u8?sec=cU6Z5ZDkxQaTuntgW-RHR8PohkswrzFTMNPEsKAhQ07-N04yZwleXMV8LiKYKpR-xvwMxZiEQSRIOau9a2OzjA&dmTs=807282&dmV1st=5107BD93C7EDE7C442E04C6DFF8839BF",
    "embedUrl": "https://www.dailymotion.com/embed/video/xamnulq",
    "duration": 2599,
    "views": 28958,
    "uploadedAt": "2026-07-08T04:59:27.000Z",
    "timestamp": 1783486767
  },
  {
    "id": "xamnzbu",
    "title": "أم التنانين التسعة",
    "thumbnail": "https://s2.dmcdn.net/v/cJr2Q1gJqO-sSFT5C",
    "m3u8Url": "https://cdndirector.dailymotion.com/cdn/manifest/video/xamnzbu.m3u8?sec=LR2zDZoWwAoVyteIYHU03cvG79TCxUj8kgJq1u50pD0pvZ6TzpwY8AmD2sU2aKQHOkXlcZTNJNkQwMmQg8WLUg&dmTs=499006&dmV1st=537C2AB92860F2D2604094B9E9DC21EA",
    "embedUrl": "https://www.dailymotion.com/embed/video/xamnzbu",
    "duration": 4255,
    "views": 21082,
    "uploadedAt": "2026-07-08T04:59:05.000Z",
    "timestamp": 1783486745
  },
  {
    "id": "xamnzby",
    "title": "بدوني، أنتم لا شيء (مدبلج)",
    "thumbnail": "https://s2.dmcdn.net/v/cJr2U1gJtJwft9lN_",
    "m3u8Url": "https://cdndirector.dailymotion.com/cdn/manifest/video/xamnzby.m3u8?sec=0mWi6foDBT2bZ_s9NDYFX926Vm4soZpk_8iBKuWQ06brQOKT1pSv3sPsLvb2Nl54vTNtRkq3Kh5f_ZeDhhkl_g&dmTs=701306&dmV1st=C30559D476939574CFCE5C1C629EDD32",
    "embedUrl": "https://www.dailymotion.com/embed/video/xamnzby",
    "duration": 5132,
    "views": 40581,
    "uploadedAt": "2026-07-08T04:58:52.000Z",
    "timestamp": 1783486732
  },
  {
    "id": "xalyt9m",
    "title": "أسطورة القزم في كرة السلة",
    "thumbnail": "https://s1.dmcdn.net/v/cFMMg1gJG52PIlF_p",
    "m3u8Url": "https://cdndirector.dailymotion.com/cdn/manifest/video/xalyt9m.m3u8?sec=eyic5mPz8-6rtdDBxGejv6JijPYJtclC68vqLPHs7hAxUIkx_RJ0yMtEzsEnywJJnqAAiwzDgSBbRIko5eANCw&dmTs=38010&dmV1st=FCACB0BDEE742A879E53834C130B1B56",
    "embedUrl": "https://www.dailymotion.com/embed/video/xalyt9m",
    "duration": 7520,
    "views": 23759,
    "uploadedAt": "2026-07-06T15:17:37.000Z",
    "timestamp": 1783351057
  },
  {
    "id": "xalyt8u",
    "title": "تمثيل صار حقيقة",
    "thumbnail": "https://s2.dmcdn.net/v/cFMME1gJDo_Nh8HWO",
    "m3u8Url": "https://cdndirector.dailymotion.com/cdn/manifest/video/xalyt8u.m3u8?sec=W05deMM96khGfIlGhAGwDL36-8o4YUFl9dh3ru4KREA1vVyTgW3oLEkoL1smJm3rXhVC2d2y_fu_NUOfgw00dg&dmTs=605725&dmV1st=E771E73B88B425BE9B15D1DD4701AEF2",
    "embedUrl": "https://www.dailymotion.com/embed/video/xalyt8u",
    "duration": 5316,
    "views": 17799,
    "uploadedAt": "2026-07-06T15:17:04.000Z",
    "timestamp": 1783351024
  }
]