[
  {
    "id": "xajo2m2",
    "title": "ابنة الفرعون الحقيقية - مشاهدة المسلسل الصيني الكامل مترجم.",
    "thumbnail": "https://s2.dmcdn.net/v/c0duw1gHHzVYFtwOC",
    "m3u8Url": "https://cdndirector.dailymotion.com/cdn/manifest/video/xajo2m2.m3u8?sec=w1MsWHMwhFG3LPvSnBSy6VY8Hz44Pcd8pGvn8uytVgnuvf1IXWWTWORiIBWeNf9ZjdbjXH4ycY5JSZUIgNILVw&dmTs=911472&dmV1st=D3F0DD4AC61D5EEBBF69822E01289803",
    "embedUrl": "https://www.dailymotion.com/embed/video/xajo2m2",
    "duration": 5839,
    "views": 15797,
    "uploadedAt": "2026-06-29T08:23:21.000Z",
    "timestamp": 1782721401
  },
  {
    "id": "xaj2paa",
    "title": "القاتل رقم صفر - مشاهدة المسلسل كامل مجاناً ",
    "thumbnail": "https://s2.dmcdn.net/v/byqU21gFwAl8QpLUX",
    "m3u8Url": "https://cdndirector.dailymotion.com/cdn/manifest/video/xaj2paa.m3u8?sec=p-2HaVNMK0kx2Cn-twhc8F8wM29IYDiwdLfpUaGeUFynHYaaQMlclmZBZNd9zwVlXhDKAnxOZo5W_gBeSBq7xw&dmTs=132099&dmV1st=444080959F7AF2877DD1D354DF198D31",
    "embedUrl": "https://www.dailymotion.com/embed/video/xaj2paa",
    "duration": 6939,
    "views": 35929,
    "uploadedAt": "2026-06-26T15:41:38.000Z",
    "timestamp": 1782488498
  },
  {
    "id": "xaip6ea",
    "title": "صعود ملكة الليكان - مشاهدة المسلسل مترجم كامل",
    "thumbnail": "https://s2.dmcdn.net/v/bwQQY1gFWrWy15dyk",
    "m3u8Url": "https://cdndirector.dailymotion.com/cdn/manifest/video/xaip6ea.m3u8?sec=Y8SWhBacJ5JVFq3q320tvNMfMwaDgx2r6D4qKeBRLqUHIOuYfhwgBYy4EuGTV6NVZ39xJ2qyveyQWtCmIKGpPg&dmTs=77249&dmV1st=52830BD100CA5C0A0EA529190359B5E0",
    "embedUrl": "https://www.dailymotion.com/embed/video/xaip6ea",
    "duration": 4210,
    "views": 16478,
    "uploadedAt": "2026-06-25T18:31:46.000Z",
    "timestamp": 1782412306
  },
  {
    "id": "xaiexqu",
    "title": "زوج متشبث، زوجة بوجهين",
    "thumbnail": "https://s2.dmcdn.net/v/bubnM1gFJ6cH68V0K",
    "m3u8Url": "https://cdndirector.dailymotion.com/cdn/manifest/video/xaiexqu.m3u8?sec=69xCtEKnM8C2AXi1_cazMnQr1uiwgVS-hv9aCXj-py7zt99zED-wrhfIk2FdnZhy1RW0Fee7u7JQdhwX_Lwfug&dmTs=982212&dmV1st=20AE6532D65E7FF048CFC914B571F419",
    "embedUrl": "https://www.dailymotion.com/embed/video/xaiexqu",
    "duration": 8474,
    "views": 32695,
    "uploadedAt": "2026-06-24T17:09:05.000Z",
    "timestamp": 1782320945
  },
  {
    "id": "xaiexqy",
    "title": "بتلات الورد والبعث",
    "thumbnail": "https://s1.dmcdn.net/v/bubnQ1gFJ9K-c2DXj",
    "m3u8Url": "https://cdndirector.dailymotion.com/cdn/manifest/video/xaiexqy.m3u8?sec=jfLfK8I3yV-mzIBXugbhrsOhwdE2NZfeEKyyNeQh9gFaDZItFcxtC86FPdcE5xcrziiA6-BJrAeGEQUgZdf2Bg&dmTs=708651&dmV1st=8BBCC687D8ECCCB9BA8F0CF49A22ADDE",
    "embedUrl": "https://www.dailymotion.com/embed/video/xaiexqy",
    "duration": 7616,
    "views": 46993,
    "uploadedAt": "2026-06-24T17:09:03.000Z",
    "timestamp": 1782320943
  },
  {
    "id": "xaiexr2",
    "title": "منعت العلاج لطفلها الخاص",
    "thumbnail": "https://s1.dmcdn.net/v/bubnU1gFIzxq93Vsn",
    "m3u8Url": "https://cdndirector.dailymotion.com/cdn/manifest/video/xaiexr2.m3u8?sec=BkUDCK-pxCsjcXQQcQ6pP-3E4C0OpQpDuNtaj3kHoBQ9ysko4yabnRM1CacXSG7bkC7DGujHFEBRQrIvrrnKBA&dmTs=814322&dmV1st=3BB1A89E303D962363E2CA5DBEAF8A28",
    "embedUrl": "https://www.dailymotion.com/embed/video/xaiexr2",
    "duration": 6016,
    "views": 16100,
    "uploadedAt": "2026-06-24T17:08:08.000Z",
    "timestamp": 1782320888
  },
  {
    "id": "xaiexqq",
    "title": "العدو الذي تزوجته",
    "thumbnail": "https://s2.dmcdn.net/v/bubnI1gFI_ZH1rD4w",
    "m3u8Url": "https://cdndirector.dailymotion.com/cdn/manifest/video/xaiexqq.m3u8?sec=muP8z1ZMtqBLnt4quxCSG4Gj5VjE-r5w08zzzD0xbLy-W-u3dJLWz7NnX_Q8Mw5w8c75LOgYvDylsGfhgGF57g&dmTs=237495&dmV1st=4436E784B21A4B4E042B0FC3A83C9105",
    "embedUrl": "https://www.dailymotion.com/embed/video/xaiexqq",
    "duration": 10309,
    "views": 30551,
    "uploadedAt": "2026-06-24T16:52:25.000Z",
    "timestamp": 1782319945
  },
  {
    "id": "xaiexqm",
    "title": "تزوجت رئيسي بالصدفة",
    "thumbnail": "https://s1.dmcdn.net/v/bubnE1gFUk2-H3oZr",
    "m3u8Url": "https://cdndirector.dailymotion.com/cdn/manifest/video/xaiexqm.m3u8?sec=tMzrOF_KjBLAJz3fKchXYrBkuq9bbin_CJ9Vh4SwFMhMbmJwh22mkQaNKqMatBSgQMpfbLQlHrCK6WFyle-oxg&dmTs=162249&dmV1st=BB07604F2A4EB3492C4CFF93DDD2310B",
    "embedUrl": "https://www.dailymotion.com/embed/video/xaiexqm",
    "duration": 3563,
    "views": 24580,
    "uploadedAt": "2026-06-24T16:50:58.000Z",
    "timestamp": 1782319858
  },
  {
    "id": "xai7pym",
    "title": " سيد الأفاعي المتيم مدبلج كامل ",
    "thumbnail": "https://s2.dmcdn.net/v/btJak1gEokcU4erb4",
    "m3u8Url": "https://cdndirector.dailymotion.com/cdn/manifest/video/xai7pym.m3u8?sec=A8AKk53eASI1VQOoEtRq2zR9aucNWnqqyQ9utChWifWqMRkxuNnphbU26cfTeFDKoU67IV4uKLp4HOkH_mEitQ&dmTs=693908&dmV1st=D893BE4312A1600192231789B33507A5",
    "embedUrl": "https://www.dailymotion.com/embed/video/xai7pym",
    "duration": 4587,
    "views": 5911,
    "uploadedAt": "2026-06-23T22:26:04.000Z",
    "timestamp": 1782253564
  },
  {
    "id": "xai6a6i",
    "title": "[مدبلج]بعد الطلاق صرت وريثة الأغنى عالميًا",
    "thumbnail": "https://s1.dmcdn.net/v/bt3CA1gEqpazU2avz",
    "m3u8Url": "https://cdndirector.dailymotion.com/cdn/manifest/video/xai6a6i.m3u8?sec=_oTEJn6RwcrpCoj99ezkQN2K0l6Hj44mRu6Wz_e1yoyQ2OMqboQCyroXaYd06Oo8bEXWL77ow9m2YF4S7tStfg&dmTs=545741&dmV1st=5146F30D400F64E1AD5F1CE6DB44489C",
    "embedUrl": "https://www.dailymotion.com/embed/video/xai6a6i",
    "duration": 6059,
    "views": 40565,
    "uploadedAt": "2026-06-23T16:44:16.000Z",
    "timestamp": 1782233056
  },
  {
    "id": "xai6a6a",
    "title": "زواج صوري من عدوي اللدود",
    "thumbnail": "https://s2.dmcdn.net/v/bt3C21gEv7QZrrB_v",
    "m3u8Url": "https://cdndirector.dailymotion.com/cdn/manifest/video/xai6a6a.m3u8?sec=-zkic-uapTcECkueaKFXp4-0tMZU6iZgzAAomOW6GFjlRnopTzuNvU3O24KD5NrpHAHe5nwDrSOJhUx2OlkINw&dmTs=833621&dmV1st=45011DD7422121FCD2532287CE6AD547",
    "embedUrl": "https://www.dailymotion.com/embed/video/xai6a6a",
    "duration": 1796,
    "views": 6297,
    "uploadedAt": "2026-06-23T16:34:39.000Z",
    "timestamp": 1782232479
  },
  {
    "id": "xahwm4m",
    "title": "تركته، فخسر كل شيء",
    "thumbnail": "https://s1.dmcdn.net/v/brL461gEPD18gjKED",
    "m3u8Url": "https://cdndirector.dailymotion.com/cdn/manifest/video/xahwm4m.m3u8?sec=ehq8zYzKFnaqBGaF9rovhtUfQkWeLj_U0fvVNThtk10a5ETl-uRZn72tfsFgbgOHZNHpWevFHrF3lg2c0pg1dg&dmTs=609655&dmV1st=01F96C35060844372DE105A7582FCF3B",
    "embedUrl": "https://www.dailymotion.com/embed/video/xahwm4m",
    "duration": 7615,
    "views": 32003,
    "uploadedAt": "2026-06-22T14:48:43.000Z",
    "timestamp": 1782139723
  },
  {
    "id": "xahwm4a",
    "title": "جائزة التشفير بعد فشل الحياة",
    "thumbnail": "https://s2.dmcdn.net/v/brL3w1gEQCiNJxhVL",
    "m3u8Url": "https://cdndirector.dailymotion.com/cdn/manifest/video/xahwm4a.m3u8?sec=YHe1fJhBPdA9_6bc6htZIKvVPT-CZLuviuiW1ue4dz0GeoB4khxKodaQVbZm9wTrY788m9leaiHu0hkZjWYuPA&dmTs=478238&dmV1st=60C16D04A1D48241283A4D7861C3EB8E",
    "embedUrl": "https://www.dailymotion.com/embed/video/xahwm4a",
    "duration": 6114,
    "views": 3325,
    "uploadedAt": "2026-06-22T14:35:23.000Z",
    "timestamp": 1782138923
  },
  {
    "id": "xahwm4e",
    "title": "لعبة حب الورثة",
    "thumbnail": "https://s1.dmcdn.net/v/brL3-1gEs72R1GzQV",
    "m3u8Url": "https://cdndirector.dailymotion.com/cdn/manifest/video/xahwm4e.m3u8?sec=sjBK8iqCeM4ONfibQOJ-mpwE3dhEKOpEXCWPKxE2_mo4FaBfhVSiLlLI86W0e_uYbrWmeemZUm4-2dQCOYseqg&dmTs=203462&dmV1st=48BA89E7826538D62418B593ECD88344",
    "embedUrl": "https://www.dailymotion.com/embed/video/xahwm4e",
    "duration": 4702,
    "views": 35387,
    "uploadedAt": "2026-06-22T14:35:11.000Z",
    "timestamp": 1782138911
  },
  {
    "id": "xahwm4i",
    "title": "لم يقع في حبك",
    "thumbnail": "https://s1.dmcdn.net/v/brL421gFI-Pu2OjmY",
    "m3u8Url": "https://cdndirector.dailymotion.com/cdn/manifest/video/xahwm4i.m3u8?sec=tsGtdVq80JF67Tzot3CD_suaKoEiWCnspQb2NLW8N4ES4Hs1NpqWZjs12mYSiOZqFhR7a8hzwG-Gn0X2L6Qpjg&dmTs=833020&dmV1st=F956470B2AB47AA054B9C7B1939B4064",
    "embedUrl": "https://www.dailymotion.com/embed/video/xahwm4i",
    "duration": 4486,
    "views": 47638,
    "uploadedAt": "2026-06-22T14:29:01.000Z",
    "timestamp": 1782138541
  },
  {
    "id": "xahjdau",
    "title": "الندم بعد فوات الأوان",
    "thumbnail": "https://s2.dmcdn.net/v/bo-CM1gDytTR1m6uh",
    "m3u8Url": "https://cdndirector.dailymotion.com/cdn/manifest/video/xahjdau.m3u8?sec=5HLHMfBq2XcpecTzp6vuI-zoVyFM9p5EqktAtTQtzxb26DVsBDe83yL_856uiAb7gneqFSgquigDN0xr3QxBaw&dmTs=405622&dmV1st=FFB90869B3C8FCD19FD6DE2ACEA3726F",
    "embedUrl": "https://www.dailymotion.com/embed/video/xahjdau",
    "duration": 6090,
    "views": 9704,
    "uploadedAt": "2026-06-21T06:37:16.000Z",
    "timestamp": 1782023836
  },
  {
    "id": "xahjdaq",
    "title": "سبع سنوات من أجل لا شيء",
    "thumbnail": "https://s1.dmcdn.net/v/bo-CI1gE6bQv5pkVO",
    "m3u8Url": "https://cdndirector.dailymotion.com/cdn/manifest/video/xahjdaq.m3u8?sec=ORcpmAS2QYiKMpzvVrh6kHl1ECb8V48TPJctH5gvme9sahkr-oWI0q4Mh2nQ1gw-Y1p5OzZU5Ym1yUZ1isRAMA&dmTs=170853&dmV1st=5F170995A5B5451765484F423FB5F748",
    "embedUrl": "https://www.dailymotion.com/embed/video/xahjdaq",
    "duration": 2433,
    "views": 31771,
    "uploadedAt": "2026-06-21T06:18:39.000Z",
    "timestamp": 1782022719
  },
  {
    "id": "xahamr2",
    "title": "عودة ملكة العنقاء: سر استبدال لـ16 عامً الحلقة  الثانية",
    "thumbnail": "https://s1.dmcdn.net/v/bnQgk1gEBG2P6Txtq",
    "m3u8Url": "https://cdndirector.dailymotion.com/cdn/manifest/video/xahamr2.m3u8?sec=Jo_zO4HosN6lxPSSwakpE1oY_PfCflRm68oQch_8Bj-U1oUg2cC-Cs_xK2dNRCLgnWBW4rKFoA_7410E94eyzA&dmTs=59277&dmV1st=9C8EAE95D051E0BDED90C2913CF92C8B",
    "embedUrl": "https://www.dailymotion.com/embed/video/xahamr2",
    "duration": 4380,
    "views": 2756,
    "uploadedAt": "2026-06-19T22:12:35.000Z",
    "timestamp": 1781907155
  },
  {
    "id": "xaha8zu",
    "title": "عودة ملكة العنقاء: سر استبدال لـ16 عامً الحلقة الاولى",
    "thumbnail": "https://s1.dmcdn.net/v/bnMKA1gEyT7s4V9ie",
    "m3u8Url": "https://cdndirector.dailymotion.com/cdn/manifest/video/xaha8zu.m3u8?sec=8_aFAe_cPuqDJ0CxCb3eiABFEqCRzv2LvU3wVNd5EvltZkdaa8x5W99yv3zYQ1Jx991X2E1OP9lI2aXyOvMozQ&dmTs=194698&dmV1st=0E42048C661D0A5CCA89E60150B5C6BB",
    "embedUrl": "https://www.dailymotion.com/embed/video/xaha8zu",
    "duration": 3066,
    "views": 12240,
    "uploadedAt": "2026-06-19T20:20:38.000Z",
    "timestamp": 1781900438
  },
  {
    "id": "xah9h5y",
    "title": "زوجي المتشرد هو أمير التنين مدبلج ",
    "thumbnail": "https://s2.dmcdn.net/v/bnDWc1gDQ9Ki5Ha-F",
    "m3u8Url": "https://cdndirector.dailymotion.com/cdn/manifest/video/xah9h5y.m3u8?sec=5t55Sv4-Y9h_AWq1XwNaLuL6l_GkhhsL7pqraaX0hBBBradSCXNhWL9TuhwlbaqSx6K7YpNmXbRlbtb1Xclndg&dmTs=429381&dmV1st=2828ECAC86592C5DE5623A997832EFDE",
    "embedUrl": "https://www.dailymotion.com/embed/video/xah9h5y",
    "duration": 5044,
    "views": 47497,
    "uploadedAt": "2026-06-19T17:27:55.000Z",
    "timestamp": 1781890075
  },
  {
    "id": "xagy9re",
    "title": "الحنان المفقود",
    "thumbnail": "https://s1.dmcdn.net/v/blDtg1gDH1Lj7AHWT",
    "m3u8Url": "https://cdndirector.dailymotion.com/cdn/manifest/video/xagy9re.m3u8?sec=qLJ4HEmrH6VhWboNrvHcN3curiDQNLx_YSOOtpLptXvHg79Vm2acqSNgod14N_gLEnUnMc_QmHnrFq2uzUPVCw&dmTs=249037&dmV1st=67303668C277C7AB3D809E72FA619288",
    "embedUrl": "https://www.dailymotion.com/embed/video/xagy9re",
    "duration": 6265,
    "views": 10816,
    "uploadedAt": "2026-06-19T02:05:40.000Z",
    "timestamp": 1781834740
  },
  {
    "id": "xagy9rq",
    "title": "الزوجة المنبوذة هي ملكة المستذئبين",
    "thumbnail": "https://s1.dmcdn.net/v/blDts1gDJDKjH9_eh",
    "m3u8Url": "https://cdndirector.dailymotion.com/cdn/manifest/video/xagy9rq.m3u8?sec=PpGhJuAPxlejEY1j8CMIG1GILGH8W1NcWqfVItWonzchzaAwd5C5E_JqZcH_a0o4xsVHRieUqb4hoLPhSN0nGQ&dmTs=921991&dmV1st=7DE3D27778BF75C72DB2407BBFF47675",
    "embedUrl": "https://www.dailymotion.com/embed/video/xagy9rq",
    "duration": 4728,
    "views": 11469,
    "uploadedAt": "2026-06-19T01:51:27.000Z",
    "timestamp": 1781833887
  },
  {
    "id": "xagy9ri",
    "title": "اللونا وفرصتها الثانية",
    "thumbnail": "https://s1.dmcdn.net/v/blDtk1gDOKHwJdJPI",
    "m3u8Url": "https://cdndirector.dailymotion.com/cdn/manifest/video/xagy9ri.m3u8?sec=F_O8q1mvT_LcLKRAnMgvfPWmzdvNNitS35tZ9Sz9M8Dog2hmZk99hC2PDJdEtVMcSj7-8vKpqY1eF-afg1Gyvw&dmTs=462717&dmV1st=9EBA30E5C7E19F4E7A7205F9F296DFE5",
    "embedUrl": "https://www.dailymotion.com/embed/video/xagy9ri",
    "duration": 4763,
    "views": 40201,
    "uploadedAt": "2026-06-19T01:50:40.000Z",
    "timestamp": 1781833840
  },
  {
    "id": "xagy9ra",
    "title": "أسطورة الملعب",
    "thumbnail": "https://s2.dmcdn.net/v/blDtc1gDJ3nQxaBW0",
    "m3u8Url": "https://cdndirector.dailymotion.com/cdn/manifest/video/xagy9ra.m3u8?sec=t3ABMwqoDCJq96AE4KpeLxKEFr5LhFEcxvGgHQF-ThBhfLej33ARnDxxoqitWpbCqH1temHAVHjrfW1SisX8Bg&dmTs=766859&dmV1st=2A3B173D6BB1A807F7119A15882C0E53",
    "embedUrl": "https://www.dailymotion.com/embed/video/xagy9ra",
    "duration": 7506,
    "views": 27401,
    "uploadedAt": "2026-06-19T01:48:38.000Z",
    "timestamp": 1781833718
  },
  {
    "id": "xagg53q",
    "title": "زوج المستأجر والحفيد الملياردير مدبلج",
    "thumbnail": "https://s2.dmcdn.net/v/bh_NM1gDR1G0-b1qn",
    "m3u8Url": "https://cdndirector.dailymotion.com/cdn/manifest/video/xagg53q.m3u8?sec=2wYtCi_OoY-mzhAdX93rJvir4YLs81waOGePiBmJfD9QVEAgfeNdSVN2YY4KS2y1LaIO4PytBh3voBKU63-75Q&dmTs=959725&dmV1st=7B0D445E2E0E37962D27580EA5E7889A",
    "embedUrl": "https://www.dailymotion.com/embed/video/xagg53q",
    "duration": 5478,
    "views": 2249,
    "uploadedAt": "2026-06-17T22:34:03.000Z",
    "timestamp": 1781735643
  },
  {
    "id": "xagf9va",
    "title": "حارس الظل المختوم__2___ (مدبلج)  ",
    "thumbnail": "https://s1.dmcdn.net/v/bhrUs1gCmbeIHtyPx",
    "m3u8Url": "https://cdndirector.dailymotion.com/cdn/manifest/video/xagf9va.m3u8?sec=_G7rXanBOb9zR-SHj6MPrJzGgvg3aTl-h7IEjdDXOxLvo7DkjpjwlYyKTFrBfZKGtBDs2rPSY-SXf6jMxDS8vQ&dmTs=683602&dmV1st=5DA3584D1C6D799871469D4C761B0D51",
    "embedUrl": "https://www.dailymotion.com/embed/video/xagf9va",
    "duration": 4143,
    "views": 1040,
    "uploadedAt": "2026-06-17T18:35:25.000Z",
    "timestamp": 1781721325
  },
  {
    "id": "xagf7ii",
    "title": "حارس الظل المختوم__1___ (مدبلج)  ",
    "thumbnail": "https://s1.dmcdn.net/v/bhqlA1gFJ7AAgYQ4G",
    "m3u8Url": "https://cdndirector.dailymotion.com/cdn/manifest/video/xagf7ii.m3u8?sec=ndN-QGFQ7YhQFjsM5KSnV9R4IIiTlRGh_LAbK5HMZviGsEBeLol_HJl2uhMUA3A57SiCnd-J1SH-ECtE01nIXw&dmTs=493267&dmV1st=801305ED119A41288B6057EF74592A1F",
    "embedUrl": "https://www.dailymotion.com/embed/video/xagf7ii",
    "duration": 3220,
    "views": 13799,
    "uploadedAt": "2026-06-17T18:18:11.000Z",
    "timestamp": 1781720291
  },
  {
    "id": "xagec9e",
    "title": "حب بعد النسيان",
    "thumbnail": "https://s1.dmcdn.net/v/bhgsI1gClO-ThjjDU",
    "m3u8Url": "https://cdndirector.dailymotion.com/cdn/manifest/video/xagec9e.m3u8?sec=pUMyGVPLzs70MHI-r7h-a0JtX5uinBFTnWZuZw6ZujOSj2c2vk_hbrcD38A1AV3qTVL6Ua_Dse9SSJ-rsRCqow&dmTs=40284&dmV1st=518E6C8D3DAFD21B73B746682597DBEE",
    "embedUrl": "https://www.dailymotion.com/embed/video/xagec9e",
    "duration": 7986,
    "views": 24611,
    "uploadedAt": "2026-06-17T15:26:28.000Z",
    "timestamp": 1781709988
  },
  {
    "id": "xag8gqa",
    "title": "ظلال اليقظة فوضى الخالدين",
    "thumbnail": "https://s1.dmcdn.net/v/bgdwo1gClY1miMFot",
    "m3u8Url": "https://cdndirector.dailymotion.com/cdn/manifest/video/xag8gqa.m3u8?sec=kwJMr6zflBqXIgyXHiSIc0pW-nDUBOT5Ec3MHkkLo6ukpHLCrjp240YsEmhvJsD_5WGMJ4_mJYdlztzQFmf7Iw&dmTs=902332&dmV1st=FE9E45F1BB83455255F11B69E574AE8E",
    "embedUrl": "https://www.dailymotion.com/embed/video/xag8gqa",
    "duration": 7100,
    "views": 27072,
    "uploadedAt": "2026-06-16T22:15:42.000Z",
    "timestamp": 1781648142
  },
  {
    "id": "xag6fgq",
    "title": "فصلي الثاني",
    "thumbnail": "https://s1.dmcdn.net/v/bgGlA1gCTbKrAoEUE",
    "m3u8Url": "https://cdndirector.dailymotion.com/cdn/manifest/video/xag6fgq.m3u8?sec=65zXU226mzadW4j4OsL2NIPfsuTSfL3tQzaeNPXzbwflbqE0qrcqcFeQu6yii3JvcH1Sj8Ff0eaxpw2IenYMIQ&dmTs=334982&dmV1st=1EA3523AB6EAB8382CE5F45CAA89DAE6",
    "embedUrl": "https://www.dailymotion.com/embed/video/xag6fgq",
    "duration": 7979,
    "views": 35238,
    "uploadedAt": "2026-06-16T16:00:33.000Z",
    "timestamp": 1781625633
  }
]