[
  {
    "id": "xarah1u",
    "title": "عذاب العشق عبر ألف عام",
    "thumbnail": "https://s1.dmcdn.net/v/cnTVI1gOWCrjvWsXp",
    "m3u8Url": "https://cdndirector.dailymotion.com/cdn/manifest/video/xarah1u.m3u8?sec=dqdEtsNBeTEbFEevrhM_VsLt92bafMmHSy0NAENtiHSDIFF59Y2EPncVAWAkEhyiTPT-jCELwoxT3bnmrVZx-A&dmTs=894332&dmV1st=D85EA821CDA2870970095BECFC59320C",
    "embedUrl": "https://www.dailymotion.com/embed/video/xarah1u",
    "duration": 11286,
    "views": 22531,
    "uploadedAt": "2026-07-22T17:05:37.000Z",
    "timestamp": 1784739937
  },
  {
    "id": "xarah1i",
    "title": "كلماتها هي الهلاك",
    "thumbnail": "https://s1.dmcdn.net/v/cnTV61gOUNhOOuv2E",
    "m3u8Url": "https://cdndirector.dailymotion.com/cdn/manifest/video/xarah1i.m3u8?sec=ND3guF0kaNSHoIkMNHhxaLE5BVMGXmyhs7cyhmtB96B_jbXEiuNp-_HVxe_Cpi7b4pfzORpuw_Z9xS25s9FCqA&dmTs=728568&dmV1st=65F7B1F707B1E14A48349191FC150433",
    "embedUrl": "https://www.dailymotion.com/embed/video/xarah1i",
    "duration": 1964,
    "views": 45964,
    "uploadedAt": "2026-07-22T17:02:23.000Z",
    "timestamp": 1784739743
  },
  {
    "id": "xarah1y",
    "title": "أسرار قصر الصقر  ليلة عرس ووريثة العرش",
    "thumbnail": "https://s2.dmcdn.net/v/cnTVM1gOFWRY6b7ic",
    "m3u8Url": "https://cdndirector.dailymotion.com/cdn/manifest/video/xarah1y.m3u8?sec=0g60-yemz4m_exInbaP801piz8J4TBXyL4H8a0s2Tv00_BM96Xmv2P3prv5raLTEb7gLecZgv0zqCQXEGsHnRg&dmTs=791234&dmV1st=7575C1AFF6FC544BF0C921521CDEFBD0",
    "embedUrl": "https://www.dailymotion.com/embed/video/xarah1y",
    "duration": 2534,
    "views": 18182,
    "uploadedAt": "2026-07-22T17:02:11.000Z",
    "timestamp": 1784739731
  },
  {
    "id": "xarah1m",
    "title": "في هذه الحياة، سأتركك",
    "thumbnail": "https://s2.dmcdn.net/v/cnTVA1gOFUN18D8CD",
    "m3u8Url": "https://cdndirector.dailymotion.com/cdn/manifest/video/xarah1m.m3u8?sec=HOj7VB-x3VumoEBIPOlDACuGyPMSBeK1bg9oygMqMvE1DFbevluq3bKFNKj8B6HsnNzqOzQf1yq-LpOWOP7dXQ&dmTs=358328&dmV1st=D1B43C584F078B5AB71EFCC204F00359",
    "embedUrl": "https://www.dailymotion.com/embed/video/xarah1m",
    "duration": 1988,
    "views": 9358,
    "uploadedAt": "2026-07-22T17:01:59.000Z",
    "timestamp": 1784739719
  },
  {
    "id": "xarah1q",
    "title": "قلادة الصدق القاتلة",
    "thumbnail": "https://s1.dmcdn.net/v/cnTVE1gOFU9Nqt6zD",
    "m3u8Url": "https://cdndirector.dailymotion.com/cdn/manifest/video/xarah1q.m3u8?sec=hjIJ7CLrbHHZWm0zFKNIrWfCOXQNoKDiMMZXebw37uQqFMrtrmX7aKw3QuaRY3-5-n0oXGsTZPq0dmelrBNKSg&dmTs=970030&dmV1st=8CD8CE63486651CC45C5062F2F04EA91",
    "embedUrl": "https://www.dailymotion.com/embed/video/xarah1q",
    "duration": 2137,
    "views": 38440,
    "uploadedAt": "2026-07-22T17:01:48.000Z",
    "timestamp": 1784739708
  },
  {
    "id": "xaqv6o6",
    "title": "أخي غير الشقيق فاقد الذاكرة يظنني حبيبته",
    "thumbnail": "https://s2.dmcdn.net/v/cklM61gOA0BUBBrZ1",
    "m3u8Url": "https://cdndirector.dailymotion.com/cdn/manifest/video/xaqv6o6.m3u8?sec=O_mbAe6Rnet361zW8_3vWvG-LH_2pDTehifgJ_U3C1OL8SIVBYZOGbpymviy3ct5OcAl7ONvSVddbPmnhqanUw&dmTs=680169&dmV1st=1870B2E46563BC16D95F80FC270DA07C",
    "embedUrl": "https://www.dailymotion.com/embed/video/xaqv6o6",
    "duration": 4208,
    "views": 7305,
    "uploadedAt": "2026-07-21T15:29:02.000Z",
    "timestamp": 1784647742
  },
  {
    "id": "xaqv6nu",
    "title": "الوريثتان المتبدلتان مصير في غير موضعه(بالعربية)",
    "thumbnail": "https://s2.dmcdn.net/v/cklLw1gO3whEfRkzV",
    "m3u8Url": "https://cdndirector.dailymotion.com/cdn/manifest/video/xaqv6nu.m3u8?sec=Jux4V2tGCcGI4WjfZr7WUcYOIm2_Qqp5BNJF-N5lJdxs-8QZEvqJh-WshTuEpV0B-pC_D6vLoLkhgZdujTFa_A&dmTs=188732&dmV1st=3A82EBF6BA3000757367B68AFE90F8EE",
    "embedUrl": "https://www.dailymotion.com/embed/video/xaqv6nu",
    "duration": 3672,
    "views": 18755,
    "uploadedAt": "2026-07-21T15:28:37.000Z",
    "timestamp": 1784647717
  },
  {
    "id": "xaqv6ny",
    "title": "فتى الإسطبل أسطورة",
    "thumbnail": "https://s2.dmcdn.net/v/cklL-1gO3j-AJ1jNZ",
    "m3u8Url": "https://cdndirector.dailymotion.com/cdn/manifest/video/xaqv6ny.m3u8?sec=FTgf2LsoinzXq7cal9z1jCpqdyjNcReIqayCRz5ac0_8zJQ4M7vwmZlCgIWaTApZE3hvOBevKUuhyILxAaBznQ&dmTs=760717&dmV1st=FC4A41B25AA7EB5F3F8FDB7A5EF0E85C",
    "embedUrl": "https://www.dailymotion.com/embed/video/xaqv6ny",
    "duration": 3851,
    "views": 7014,
    "uploadedAt": "2026-07-21T15:28:28.000Z",
    "timestamp": 1784647708
  },
  {
    "id": "xaqt3la",
    "title": "مشاهدة مسلسل المنتقم المنفلت مترجم كامل",
    "thumbnail": "https://s1.dmcdn.net/v/ckNbk1gNsHrTZ4QyR",
    "m3u8Url": "https://cdndirector.dailymotion.com/cdn/manifest/video/xaqt3la.m3u8?sec=VVHNQQ01WlZfC67CxLGZ5a9A9laJF_JbbjBHqIu2tCSl87E0tqJ0HD6NWLTJLTAViaEyb-s1zRQ-iYZvEzbj3w&dmTs=422577&dmV1st=6394CB0B6445606EA2CAD23CA3C5AC26",
    "embedUrl": "https://www.dailymotion.com/embed/video/xaqt3la",
    "duration": 5916,
    "views": 31740,
    "uploadedAt": "2026-07-20T21:38:02.000Z",
    "timestamp": 1784583482
  },
  {
    "id": "xaqq34i",
    "title": "بعد الفوات، لا عودة",
    "thumbnail": "https://s1.dmcdn.net/v/cjrHI1gNlHdFE0I1I",
    "m3u8Url": "https://cdndirector.dailymotion.com/cdn/manifest/video/xaqq34i.m3u8?sec=TGz7ZCrIeVDOv2FF3pMsyX-r9UuT5bfg63t2qYvtBw30fS3PeG21I9RdHcxaHipSpDafmF3Y1zFAMYskPMKSAg&dmTs=297274&dmV1st=4D06D64B99BBE40B397B879C53C03283",
    "embedUrl": "https://www.dailymotion.com/embed/video/xaqq34i",
    "duration": 7622,
    "views": 45631,
    "uploadedAt": "2026-07-20T15:24:57.000Z",
    "timestamp": 1784561097
  },
  {
    "id": "xaqq34m",
    "title": "ماضٍ غارق تحت ضوء القمر",
    "thumbnail": "https://s2.dmcdn.net/v/cjrHM1gNsyUQnz7E_",
    "m3u8Url": "https://cdndirector.dailymotion.com/cdn/manifest/video/xaqq34m.m3u8?sec=inJnPK4XPn9CITutlUjln1EEfP2Hbuo8POcM3fLWxAyKems23wIVFeJO4kOlqEK3dJmRt8ocSdwJL9JzSgf4RA&dmTs=45976&dmV1st=EB3EBF7255F36B5610C0102D62FEFF40",
    "embedUrl": "https://www.dailymotion.com/embed/video/xaqq34m",
    "duration": 9416,
    "views": 37000,
    "uploadedAt": "2026-07-20T15:24:49.000Z",
    "timestamp": 1784561089
  },
  {
    "id": "xaqq9ge",
    "title": "سقوط نجم الظهيرة",
    "thumbnail": "https://s1.dmcdn.net/v/cjtHU1gNpL0iTxHe_",
    "m3u8Url": "https://cdndirector.dailymotion.com/cdn/manifest/video/xaqq9ge.m3u8?sec=6m4fw6cvzcFScJinzI0ehH-mk3Sz-27TLozlZxcqR4uFRE4PGb89fdL7nIoAPd9yWeJ16MO0uQT2ZxXv1NThnQ&dmTs=909851&dmV1st=1FFAC08F39BD0815C6F2A242ADA7DBB5",
    "embedUrl": "https://www.dailymotion.com/embed/video/xaqq9ge",
    "duration": 8340,
    "views": 25619,
    "uploadedAt": "2026-07-20T15:24:40.000Z",
    "timestamp": 1784561080
  },
  {
    "id": "xaqklv2",
    "title": "من السجن إلى العرش",
    "thumbnail": "https://s2.dmcdn.net/v/cissk1gNXFK7S7vQL",
    "m3u8Url": "https://cdndirector.dailymotion.com/cdn/manifest/video/xaqklv2.m3u8?sec=hsq6rW462dvVNDEpBJOqmNc_Ku1KotD-P5gg4cPHElrnyhc1f10-kFersz6Pnr4jn5R0S-e0vmy7P3Q-5kxi5g&dmTs=326640&dmV1st=A895B4083075E3552924B10DEEE9E4E1",
    "embedUrl": "https://www.dailymotion.com/embed/video/xaqklv2",
    "duration": 6147,
    "views": 49574,
    "uploadedAt": "2026-07-20T01:43:07.000Z",
    "timestamp": 1784511787
  },
  {
    "id": "xaqkluq",
    "title": "الشريرة التي غيرت مصيرها",
    "thumbnail": "https://s1.dmcdn.net/v/cissY1gNn2ftQelD2",
    "m3u8Url": "https://cdndirector.dailymotion.com/cdn/manifest/video/xaqkluq.m3u8?sec=eChzp2mD5zT5zlFrkLKmBQEkomGBJRhn0DBQgC_bOuaQ4LsUvRRhC8_MlPiqz_tDV21f-pHp3trts82V9Ukzcw&dmTs=599280&dmV1st=880739E6872462653BFD1E6FB7577F03",
    "embedUrl": "https://www.dailymotion.com/embed/video/xaqkluq",
    "duration": 6754,
    "views": 37911,
    "uploadedAt": "2026-07-20T01:38:29.000Z",
    "timestamp": 1784511509
  },
  {
    "id": "xaqkluy",
    "title": "زوجي خادم الإسطبل كان ملكًا",
    "thumbnail": "https://s1.dmcdn.net/v/cissg1gNh1mbJDXkc",
    "m3u8Url": "https://cdndirector.dailymotion.com/cdn/manifest/video/xaqkluy.m3u8?sec=GBp9YDP0ohgivH-1eVDUrQh5MbDg0iKM11ziDW4vVbLdnzqHn5VAQUk9yEayVBEI2qBCSG96HsMx7pS-e-OYMA&dmTs=992786&dmV1st=735BE605D024FFF9364636DC53E45F99",
    "embedUrl": "https://www.dailymotion.com/embed/video/xaqkluy",
    "duration": 4011,
    "views": 48141,
    "uploadedAt": "2026-07-20T01:35:46.000Z",
    "timestamp": 1784511346
  },
  {
    "id": "xaq7xru",
    "title": "ملك القتال المتمرّد",
    "thumbnail": "https://s2.dmcdn.net/v/cgcYw1gN7_x-mKg1D",
    "m3u8Url": "https://cdndirector.dailymotion.com/cdn/manifest/video/xaq7xru.m3u8?sec=VENEpx_j6xLHBEnw33lIscrZilLKfWj6iS6BvxiGgr7SRIoIjaqW57hhakw7oEU7xbE9ZFB36lNO6Z8WgBUX3g&dmTs=630847&dmV1st=404C3A5FBC0AA1C8BF409DC0D3796754",
    "embedUrl": "https://www.dailymotion.com/embed/video/xaq7xru",
    "duration": 5293,
    "views": 6292,
    "uploadedAt": "2026-07-18T15:36:24.000Z",
    "timestamp": 1784388984
  },
  {
    "id": "xaq5jwi",
    "title": "ماضٍ غارق تحت ضوء القمر",
    "thumbnail": "https://s1.dmcdn.net/v/cgBO21gM_FTdMkwL_",
    "m3u8Url": "https://cdndirector.dailymotion.com/cdn/manifest/video/xaq5jwi.m3u8?sec=LTWd6oiOChxNrBHgvbNrRqQrIN4Uv8E5FFZD6oy0ZTDAXBua6vMmvK18osY-JvlVVlWLY3xp0asGSI4nUtMZng&dmTs=54824&dmV1st=D90A7DA56AD97C9C299BBDDFBBD50C60",
    "embedUrl": "https://www.dailymotion.com/embed/video/xaq5jwi",
    "duration": 9416,
    "views": 20875,
    "uploadedAt": "2026-07-18T09:20:51.000Z",
    "timestamp": 1784366451
  },
  {
    "id": "xaq2e0a",
    "title": "مسلسل ثلاثون عاماً من الحماية والخيانة مترجم كامل   3",
    "thumbnail": "https://s1.dmcdn.net/v/cfdLg1gNBBZlKub1a",
    "m3u8Url": "https://cdndirector.dailymotion.com/cdn/manifest/video/xaq2e0a.m3u8?sec=aVwNyfGTE1U34tTp3s95CGtVjWd-q0dFk0aJGls7covkgytrG35u-8ngQtL8Ac-dFC0-h5oi2IV4nCwWG_AYCw&dmTs=826890&dmV1st=D5797839B0E3CDF228599C6B3BB4589E",
    "embedUrl": "https://www.dailymotion.com/embed/video/xaq2e0a",
    "duration": 601,
    "views": 44873,
    "uploadedAt": "2026-07-17T23:25:49.000Z",
    "timestamp": 1784330749
  },
  {
    "id": "xaq2d5u",
    "title": "مسلسل ثلاثون عاماً من الحماية والخيانة مترجم كامل   2",
    "thumbnail": "https://s2.dmcdn.net/v/cfd4Y1gN8dqRpXRtr",
    "m3u8Url": "https://cdndirector.dailymotion.com/cdn/manifest/video/xaq2d5u.m3u8?sec=aQ0WHSmkaSgg0MbjRlNmK39_CB_ByRiq4zA95-AhoV1ma6ydnYLTTw5bgQzVmlBYUfFrRffKn4hf0hwb1TE9Hw&dmTs=441193&dmV1st=03367096174A70CE0D2E7E676DB92176",
    "embedUrl": "https://www.dailymotion.com/embed/video/xaq2d5u",
    "duration": 603,
    "views": 6627,
    "uploadedAt": "2026-07-17T23:22:03.000Z",
    "timestamp": 1784330523
  },
  {
    "id": "xaq108q",
    "title": "مشاهدة مسلسل ثلاثون عاماً من الحماية والخيانة مترجم كامل مجانا.",
    "thumbnail": "https://s1.dmcdn.net/v/cfNbw1gN1uTCsQ7A9",
    "m3u8Url": "https://cdndirector.dailymotion.com/cdn/manifest/video/xaq108q.m3u8?sec=DY0MCIapW0410CtxsM2NuVFjko-BKbOXdVXTDsehFjA2CAfd73uaR59TMlRqLUlwA8nLTn4gbs4QqBFzGn5PIg&dmTs=326450&dmV1st=EDB8C349ACFCE419DFA02B3951503662",
    "embedUrl": "https://www.dailymotion.com/embed/video/xaq108q",
    "duration": 683,
    "views": 44147,
    "uploadedAt": "2026-07-17T18:52:15.000Z",
    "timestamp": 1784314335
  },
  {
    "id": "xapyo7u",
    "title": "مشاهدة مسلسل انتقام زوجة الرئيس مترجم كامل بجميع حلقاته بجودة عالية",
    "thumbnail": "https://s1.dmcdn.net/v/cez0Q1gN0V2IYJLKC",
    "m3u8Url": "https://cdndirector.dailymotion.com/cdn/manifest/video/xapyo7u.m3u8?sec=i_tuZsYuN8XIh6YZxVQGOJASPQVXstD5q7ovjLJWuMOkFyDArTcOVRL7q56SGzG8hmOeicE8lM5eHuS1X2tSjQ&dmTs=240493&dmV1st=302FF658D662C62BB936D730CC27222B",
    "embedUrl": "https://www.dailymotion.com/embed/video/xapyo7u",
    "duration": 4480,
    "views": 9794,
    "uploadedAt": "2026-07-17T13:27:01.000Z",
    "timestamp": 1784294821
  },
  {
    "id": "xap78m2",
    "title": "عندما يغضب الأب",
    "thumbnail": "https://s1.dmcdn.net/v/ca4XQ1gLjIPkYmPLU",
    "m3u8Url": "https://cdndirector.dailymotion.com/cdn/manifest/video/xap78m2.m3u8?sec=sERrE_2Lb96F-uNGFPUfxJI0_eKiBeZr3CDaWFEczfW4HLHEM_Id-wAv0GrnBqzLWstHPnaMkm3XurN5CxjFXg&dmTs=992479&dmV1st=91D682B579EF2C97CDF242AA2BBB009F",
    "embedUrl": "https://www.dailymotion.com/embed/video/xap78m2",
    "duration": 5072,
    "views": 39558,
    "uploadedAt": "2026-07-14T15:48:06.000Z",
    "timestamp": 1784044086
  },
  {
    "id": "xap78lu",
    "title": "بريق الانتقام",
    "thumbnail": "https://s2.dmcdn.net/v/ca4XI1gLstOBDle9H",
    "m3u8Url": "https://cdndirector.dailymotion.com/cdn/manifest/video/xap78lu.m3u8?sec=inUdDNlkUcwDXTYX3C__jVpZ58dTv1YLc5GfkRI5_ec3KAVrzEjXPBjyqMAr9OX96ijEWVj8QAf3mPUsKqz49w&dmTs=412517&dmV1st=DA6943997FD55E89BA6E353FB34788D8",
    "embedUrl": "https://www.dailymotion.com/embed/video/xap78lu",
    "duration": 3724,
    "views": 20477,
    "uploadedAt": "2026-07-14T15:45:01.000Z",
    "timestamp": 1784043901
  },
  {
    "id": "xap6s8e",
    "title": "طريق الخلود",
    "thumbnail": "https://s2.dmcdn.net/v/cZ_Lk1gMXu8tpFnZl",
    "m3u8Url": "https://cdndirector.dailymotion.com/cdn/manifest/video/xap6s8e.m3u8?sec=EVz_pS2mMEwYpjpJtO8adcNzwavIYoXT0fVE9qZgsnslh1UBTMAjiFvOJfw3w34j_Qfxmk64Ysgq_FfcFc4Ogg&dmTs=859638&dmV1st=812485D212889BE8C914A2B3AEBE1338",
    "embedUrl": "https://www.dailymotion.com/embed/video/xap6s8e",
    "duration": 7723,
    "views": 22910,
    "uploadedAt": "2026-07-14T14:58:17.000Z",
    "timestamp": 1784041097
  },
  {
    "id": "xap6s8a",
    "title": "حين أسقطت الحب من يديها",
    "thumbnail": "https://s2.dmcdn.net/v/cZ_Lg1gNLiweR603Q",
    "m3u8Url": "https://cdndirector.dailymotion.com/cdn/manifest/video/xap6s8a.m3u8?sec=3u5DTq031lBdRwSqmA1KL194k-xB8p7jFN63c0S7UHVovC1tEqZPNz5Qrepi8HgQMo3r_0ONmRuRubaXqogTfg&dmTs=529954&dmV1st=19D52C8B8908463D72601E4649CC1102",
    "embedUrl": "https://www.dailymotion.com/embed/video/xap6s8a",
    "duration": 3015,
    "views": 1174,
    "uploadedAt": "2026-07-14T14:56:43.000Z",
    "timestamp": 1784041003
  },
  {
    "id": "xap6s86",
    "title": "دينُ السيف",
    "thumbnail": "https://s1.dmcdn.net/v/cZ_Lc1gMfTWr5qXfK",
    "m3u8Url": "https://cdndirector.dailymotion.com/cdn/manifest/video/xap6s86.m3u8?sec=xBk_qf2cgjhD38SWvTOi-dxcPpNc-aWzTPyxkdfFxfe1mJFNKzcBQUo3d_cZybb_nwXCq8SZcEmU8hagxV5jMg&dmTs=416891&dmV1st=5DEB134F9014B9A64E7466250F801A81",
    "embedUrl": "https://www.dailymotion.com/embed/video/xap6s86",
    "duration": 6178,
    "views": 9204,
    "uploadedAt": "2026-07-14T14:56:33.000Z",
    "timestamp": 1784040993
  },
  {
    "id": "xaox2p6",
    "title": "سرقت أختي حبيبي، فحصلت أنا على الإمبراطور",
    "thumbnail": "https://s2.dmcdn.net/v/cYGlg1gMimGxwqF6E",
    "m3u8Url": "https://cdndirector.dailymotion.com/cdn/manifest/video/xaox2p6.m3u8?sec=gB8VUsfi5KdWxj5-qWFJmDlGc5a7lXqC8XQv_CkZHN0iDKJy9D-PjAJq-o9z7XRyUaESeFENIM2UQp6tuCSdoQ&dmTs=719086&dmV1st=70907FF1BF224F3BE8696E8DD7DB5011",
    "embedUrl": "https://www.dailymotion.com/embed/video/xaox2p6",
    "duration": 3908,
    "views": 4726,
    "uploadedAt": "2026-07-13T17:18:33.000Z",
    "timestamp": 1783963113
  },
  {
    "id": "xaodvvu",
    "title": "ساحر أفالون(بالعربية)",
    "thumbnail": "https://s2.dmcdn.net/v/cUsAg1gLYI822XYp2",
    "m3u8Url": "https://cdndirector.dailymotion.com/cdn/manifest/video/xaodvvu.m3u8?sec=GO93cGyr-CDKBBADsRfz7hVi-QPNrKNSWfhfXCADB6NGjiVq4Kp7bXvNEMSo9HcTYcn3QDl5kevW0PKR-bvpZw&dmTs=458802&dmV1st=FA1690CAE1B63CBC143578C3DB153FE6",
    "embedUrl": "https://www.dailymotion.com/embed/video/xaodvvu",
    "duration": 4112,
    "views": 3350,
    "uploadedAt": "2026-07-11T15:54:41.000Z",
    "timestamp": 1783785281
  },
  {
    "id": "xaodvvq",
    "title": "ساحة المبارزة  أستدعي الآلهة لإنقاذ العالم",
    "thumbnail": "https://s1.dmcdn.net/v/cUsAc1gLFqPNEz7Oq",
    "m3u8Url": "https://cdndirector.dailymotion.com/cdn/manifest/video/xaodvvq.m3u8?sec=nC1Pndf9ET26xqVoJwFW5vf55ztATkw2Sd9O6nzHlWMT3s6xRbBzDE0u6gXqXV-CUnsJrQuKkNTbn7qdYUHG_w&dmTs=258382&dmV1st=B35C24349076AB76F4FF2D9888C3B0C2",
    "embedUrl": "https://www.dailymotion.com/embed/video/xaodvvq",
    "duration": 4779,
    "views": 35646,
    "uploadedAt": "2026-07-11T15:54:28.000Z",
    "timestamp": 1783785268
  },
  {
    "id": "xaodjlq",
    "title": "وفاء الثعبان",
    "thumbnail": "https://s2.dmcdn.net/v/cUoH-1gLPJ_h0ui7F",
    "m3u8Url": "https://cdndirector.dailymotion.com/cdn/manifest/video/xaodjlq.m3u8?sec=fLeq5c2K_TR6dYAWMeJ-7sPLs6O-H2mpycSEeITUQXutUCOsEfiuDka5WQDlrAo_z1YYhY-vjrg4YeHowU-Xdg&dmTs=612359&dmV1st=5CC499E94519374AE0B28217859B4028",
    "embedUrl": "https://www.dailymotion.com/embed/video/xaodjlq",
    "duration": 7188,
    "views": 5586,
    "uploadedAt": "2026-07-11T10:56:33.000Z",
    "timestamp": 1783767393
  }
]