[
  {
    "title": "Beinsports 1 HD",
    "image": "https://online.aflam4you.org/uploads/thumbs/68-1.jpg",
    "playerServer": "https://online.aflam4you.org/playeraf.php?vid=68"
  },
  {
    "title": "Beinsports 2 HD",
    "image": "https://online.aflam4you.org/uploads/thumbs/2-1.jpg",
    "playerServer": "https://online.aflam4you.org/playeraf.php?vid=2"
  },
  {
    "title": "Beinsports 3 HD",
    "image": "https://online.aflam4you.org/uploads/thumbs/1-1.jpg",
    "playerServer": "https://online.aflam4you.org/playeraf.php?vid=1"
  },
  {
    "title": "الرياضية",
    "image": "https://online.aflam4you.org/uploads/thumbs/4-1.jpg",
    "playerServer": "https://online.aflam4you.org/playeraf.php?vid=4"
  },
  {
    "title": "Beinsports 4 HD",
    "image": "https://online.aflam4you.org/uploads/thumbs/3-1.jpg",
    "playerServer": "https://online.aflam4you.org/playeraf.php?vid=3"
  },
  {
    "title": "Beinsports 5 HD",
    "image": "https://online.aflam4you.org/uploads/thumbs/73-1.jpg",
    "playerServer": "https://online.aflam4you.org/playeraf.php?vid=73"
  },
  {
    "title": "Beinsports 8 HD",
    "image": "https://online.aflam4you.org/uploads/thumbs/76-1.jpg",
    "playerServer": "https://online.aflam4you.org/playeraf.php?vid=76"
  },
  {
    "title": "Bein sport 9 HD",
    "image": "https://online.aflam4you.org/uploads/thumbs/69-1.jpg",
    "playerServer": "https://online.aflam4you.org/playeraf.php?vid=69"
  },
  {
    "title": "Beinsports 6 HD",
    "image": "https://online.aflam4you.org/uploads/thumbs/74-1.jpg",
    "playerServer": "https://online.aflam4you.org/playeraf.php?vid=74"
  },
  {
    "title": "Beinsports 7 HD",
    "image": "https://online.aflam4you.org/uploads/thumbs/75-1.jpg",
    "playerServer": "https://online.aflam4you.org/playeraf.php?vid=75"
  },
  {
    "title": "بي ان سبورت الإخبارية",
    "image": "https://online.aflam4you.org/uploads/thumbs/31-1.jpg",
    "playerServer": "https://online.aflam4you.org/playeraf.php?vid=31"
  },
  {
    "title": "Beinsports Max 1",
    "image": "https://online.aflam4you.org/uploads/thumbs/179-1.jpg",
    "playerServer": "https://online.aflam4you.org/playeraf.php?vid=179"
  },
  {
    "title": "ابوظبي الرياضية 3",
    "image": "https://online.aflam4you.org/uploads/thumbs/32-1.jpg",
    "playerServer": "https://online.aflam4you.org/playeraf.php?vid=32"
  },
  {
    "title": "Beinsports 10 HD",
    "image": "https://online.aflam4you.org/uploads/thumbs/30-1.jpg",
    "playerServer": "https://online.aflam4you.org/playeraf.php?vid=30"
  },
  {
    "title": "SSC 1 Sports",
    "image": "https://online.aflam4you.org/uploads/thumbs/167-1.jpg",
    "playerServer": "https://online.aflam4you.org/playeraf.php?vid=167"
  },
  {
    "title": "Beinsports 11 HD",
    "image": "https://online.aflam4you.org/uploads/thumbs/28-1.jpg",
    "playerServer": "https://online.aflam4you.org/playeraf.php?vid=28"
  },
  {
    "title": "نايل سبورت",
    "image": "https://online.aflam4you.org/templates/aflam25555/img/echo-lzld.png",
    "playerServer": "https://online.aflam4you.org/playeraf.php?vid=34"
  },
  {
    "title": "الكأس 1",
    "image": "https://online.aflam4you.org/templates/aflam25555/img/echo-lzld.png",
    "playerServer": "https://online.aflam4you.org/playeraf.php?vid=108"
  },
  {
    "title": "Beinsports 12 HD",
    "image": "https://online.aflam4you.org/templates/aflam25555/img/echo-lzld.png",
    "playerServer": "https://online.aflam4you.org/playeraf.php?vid=29"
  },
  {
    "title": "Beinsports Max 2",
    "image": "https://online.aflam4you.org/templates/aflam25555/img/echo-lzld.png",
    "playerServer": "https://online.aflam4you.org/playeraf.php?vid=180"
  },
  {
    "title": "ON TIME SPORTS 1",
    "image": "https://online.aflam4you.org/templates/aflam25555/img/echo-lzld.png",
    "playerServer": "https://online.aflam4you.org/playeraf.php?vid=445"
  },
  {
    "title": "السعودية الرياضية 1",
    "image": "https://online.aflam4you.org/templates/aflam25555/img/echo-lzld.png",
    "playerServer": "https://online.aflam4you.org/playeraf.php?vid=57"
  },
  {
    "title": "قناة الأهلي",
    "image": "https://online.aflam4you.org/templates/aflam25555/img/echo-lzld.png",
    "playerServer": "https://online.aflam4you.org/playeraf.php?vid=27"
  },
  {
    "title": "ON Sport",
    "image": "https://online.aflam4you.org/templates/aflam25555/img/echo-lzld.png",
    "playerServer": "https://online.aflam4you.org/playeraf.php?vid=212"
  },
  {
    "title": "Beinsports HD",
    "image": "https://online.aflam4you.org/templates/aflam25555/img/echo-lzld.png",
    "playerServer": "https://online.aflam4you.org/playeraf.php?vid=117"
  },
  {
    "title": "ON TIME SPORTS 3",
    "image": "https://online.aflam4you.org/templates/aflam25555/img/echo-lzld.png",
    "playerServer": "https://online.aflam4you.org/playeraf.php?vid=65"
  },
  {
    "title": "ON TIME SPORTS 2",
    "image": "https://online.aflam4you.org/templates/aflam25555/img/echo-lzld.png",
    "playerServer": "https://online.aflam4you.org/playeraf.php?vid=33"
  },
  {
    "title": "قناة مصارع",
    "image": "https://online.aflam4you.org/templates/aflam25555/img/echo-lzld.png",
    "playerServer": "https://online.aflam4you.org/playeraf.php?vid=45"
  },
  {
    "title": "الكأس 2",
    "image": "https://online.aflam4you.org/templates/aflam25555/img/echo-lzld.png",
    "playerServer": "https://online.aflam4you.org/playeraf.php?vid=109"
  },
  {
    "title": "Beinsports 1 Premium",
    "image": "https://online.aflam4you.org/templates/aflam25555/img/echo-lzld.png",
    "playerServer": "https://online.aflam4you.org/playeraf.php?vid=1010"
  },
  {
    "title": "ابوظبي الرياضية 1",
    "image": "https://online.aflam4you.org/templates/aflam25555/img/echo-lzld.png",
    "playerServer": "https://online.aflam4you.org/playeraf.php?vid=112"
  },
  {
    "title": "الرياضية TNT",
    "image": "https://online.aflam4you.org/templates/aflam25555/img/echo-lzld.png",
    "playerServer": "https://online.aflam4you.org/playeraf.php?vid=2003"
  },
  {
    "title": "ابوظبي الرياضية 2",
    "image": "https://online.aflam4you.org/templates/aflam25555/img/echo-lzld.png",
    "playerServer": "https://online.aflam4you.org/playeraf.php?vid=114"
  },
  {
    "title": "Beinsports Max 3",
    "image": "https://online.aflam4you.org/templates/aflam25555/img/echo-lzld.png",
    "playerServer": "https://online.aflam4you.org/playeraf.php?vid=333"
  },
  {
    "title": "SSC 2 Sports",
    "image": "https://online.aflam4you.org/templates/aflam25555/img/echo-lzld.png",
    "playerServer": "https://online.aflam4you.org/playeraf.php?vid=104"
  },
  {
    "title": "الكأس 4",
    "image": "https://online.aflam4you.org/templates/aflam25555/img/echo-lzld.png",
    "playerServer": "https://online.aflam4you.org/playeraf.php?vid=2353"
  },
  {
    "title": "الكأس 3",
    "image": "https://online.aflam4you.org/templates/aflam25555/img/echo-lzld.png",
    "playerServer": "https://online.aflam4you.org/playeraf.php?vid=2352"
  },
  {
    "title": "Beinsports 2 Premium",
    "image": "https://online.aflam4you.org/templates/aflam25555/img/echo-lzld.png",
    "playerServer": "https://online.aflam4you.org/playeraf.php?vid=2020"
  },
  {
    "title": "Bein Asian cup 1",
    "image": "https://online.aflam4you.org/templates/aflam25555/img/echo-lzld.png",
    "playerServer": "https://online.aflam4you.org/playeraf.php?vid=24003"
  },
  {
    "title": "Beinsports Max 4",
    "image": "https://online.aflam4you.org/templates/aflam25555/img/echo-lzld.png",
    "playerServer": "https://online.aflam4you.org/playeraf.php?vid=444"
  },
  {
    "title": "Beinsports 3 Premium",
    "image": "https://online.aflam4you.org/templates/aflam25555/img/echo-lzld.png",
    "playerServer": "https://online.aflam4you.org/playeraf.php?vid=3030"
  },
  {
    "title": "Bein AFCON 1",
    "image": "https://online.aflam4you.org/templates/aflam25555/img/echo-lzld.png",
    "playerServer": "https://online.aflam4you.org/playeraf.php?vid=24024"
  },
  {
    "title": "الكاس extra 1",
    "image": "https://online.aflam4you.org/templates/aflam25555/img/echo-lzld.png",
    "playerServer": "https://online.aflam4you.org/playeraf.php?vid=2022"
  },
  {
    "title": "SSC extrat 1 Sports",
    "image": "https://online.aflam4you.org/templates/aflam25555/img/echo-lzld.png",
    "playerServer": "https://online.aflam4you.org/playeraf.php?vid=998"
  },
  {
    "title": "SSC 5 Sports",
    "image": "https://online.aflam4you.org/templates/aflam25555/img/echo-lzld.png",
    "playerServer": "https://online.aflam4you.org/playeraf.php?vid=116"
  },
  {
    "title": "ابوظبي الرياضية 4",
    "image": "https://online.aflam4you.org/templates/aflam25555/img/echo-lzld.png",
    "playerServer": "https://online.aflam4you.org/playeraf.php?vid=101"
  },
  {
    "title": "SSC 3 Sports",
    "image": "https://online.aflam4you.org/templates/aflam25555/img/echo-lzld.png",
    "playerServer": "https://online.aflam4you.org/playeraf.php?vid=105"
  },
  {
    "title": "العراقية الرياضية",
    "image": "https://online.aflam4you.org/templates/aflam25555/img/echo-lzld.png",
    "playerServer": "https://online.aflam4you.org/playeraf.php?vid=107"
  },
  {
    "title": "Beinsports Max 5",
    "image": "https://online.aflam4you.org/templates/aflam25555/img/echo-lzld.png",
    "playerServer": "https://online.aflam4you.org/playeraf.php?vid=5555"
  },
  {
    "title": "Beinsports Max 6",
    "image": "https://online.aflam4you.org/templates/aflam25555/img/echo-lzld.png",
    "playerServer": "https://online.aflam4you.org/playeraf.php?vid=6666"
  },
  {
    "title": "beIN Sports 1 xtra",
    "image": "https://online.aflam4you.org/templates/aflam25555/img/echo-lzld.png",
    "playerServer": "https://online.aflam4you.org/playeraf.php?vid=1001"
  },
  {
    "title": "الوطنية الرياضية",
    "image": "https://online.aflam4you.org/templates/aflam25555/img/echo-lzld.png",
    "playerServer": "https://online.aflam4you.org/playeraf.php?vid=1171"
  },
  {
    "title": "Bein Sports 4K",
    "image": "https://online.aflam4you.org/templates/aflam25555/img/echo-lzld.png",
    "playerServer": "https://online.aflam4you.org/playeraf.php?vid=44444"
  },
  {
    "title": "beIN Sports 2 xtra",
    "image": "https://online.aflam4you.org/templates/aflam25555/img/echo-lzld.png",
    "playerServer": "https://online.aflam4you.org/playeraf.php?vid=1002"
  },
  {
    "title": "SSC 4 Sports",
    "image": "https://online.aflam4you.org/templates/aflam25555/img/echo-lzld.png",
    "playerServer": "https://online.aflam4you.org/playeraf.php?vid=106"
  },
  {
    "title": "ad Sport 1 Premium",
    "image": "https://online.aflam4you.org/templates/aflam25555/img/echo-lzld.png",
    "playerServer": "https://online.aflam4you.org/playeraf.php?vid=2001"
  },
  {
    "title": "الرياضية 1",
    "image": "https://online.aflam4you.org/templates/aflam25555/img/echo-lzld.png",
    "playerServer": "https://online.aflam4you.org/playeraf.php?vid=4377"
  },
  {
    "title": "SSC extrat 2 Sports",
    "image": "https://online.aflam4you.org/templates/aflam25555/img/echo-lzld.png",
    "playerServer": "https://online.aflam4you.org/playeraf.php?vid=999"
  },
  {
    "title": "ابوظبي الرياضية 5",
    "image": "https://online.aflam4you.org/templates/aflam25555/img/echo-lzld.png",
    "playerServer": "https://online.aflam4you.org/playeraf.php?vid=102"
  },
  {
    "title": "ثمانية 1",
    "image": "https://online.aflam4you.org/templates/aflam25555/img/echo-lzld.png",
    "playerServer": "https://online.aflam4you.org/playeraf.php?vid=9311"
  },
  {
    "title": "ابوظبي الرياضية 6",
    "image": "https://online.aflam4you.org/templates/aflam25555/img/echo-lzld.png",
    "playerServer": "https://online.aflam4you.org/playeraf.php?vid=103"
  },
  {
    "title": "Sport TV 1",
    "image": "https://online.aflam4you.org/templates/aflam25555/img/echo-lzld.png",
    "playerServer": "https://online.aflam4you.org/playeraf.php?vid=5407"
  },
  {
    "title": "الكاس extra 2",
    "image": "https://online.aflam4you.org/templates/aflam25555/img/echo-lzld.png",
    "playerServer": "https://online.aflam4you.org/playeraf.php?vid=2023"
  },
  {
    "title": "BeinSports AFC 1",
    "image": "https://online.aflam4you.org/templates/aflam25555/img/echo-lzld.png",
    "playerServer": "https://online.aflam4you.org/playeraf.php?vid=24001"
  },
  {
    "title": "ad Sport 2 Premium",
    "image": "https://online.aflam4you.org/templates/aflam25555/img/echo-lzld.png",
    "playerServer": "https://online.aflam4you.org/playeraf.php?vid=2002"
  },
  {
    "title": "اعادة مباريات",
    "image": "https://online.aflam4you.org/templates/aflam25555/img/echo-lzld.png",
    "playerServer": "https://online.aflam4you.org/playeraf.php?vid=22222"
  },
  {
    "title": "Bein Asian cup 2",
    "image": "https://online.aflam4you.org/templates/aflam25555/img/echo-lzld.png",
    "playerServer": "https://online.aflam4you.org/playeraf.php?vid=24004"
  },
  {
    "title": "الكأس 5",
    "image": "https://online.aflam4you.org/templates/aflam25555/img/echo-lzld.png",
    "playerServer": "https://online.aflam4you.org/playeraf.php?vid=6424"
  },
  {
    "title": "Bein AFCON 2",
    "image": "https://online.aflam4you.org/templates/aflam25555/img/echo-lzld.png",
    "playerServer": "https://online.aflam4you.org/playeraf.php?vid=24025"
  },
  {
    "title": "BeinSports AFC 2",
    "image": "https://online.aflam4you.org/templates/aflam25555/img/echo-lzld.png",
    "playerServer": "https://online.aflam4you.org/playeraf.php?vid=24002"
  },
  {
    "title": "الكأس 6",
    "image": "https://online.aflam4you.org/templates/aflam25555/img/echo-lzld.png",
    "playerServer": "https://online.aflam4you.org/playeraf.php?vid=8281"
  },
  {
    "title": "Sport TV 5",
    "image": "https://online.aflam4you.org/templates/aflam25555/img/echo-lzld.png",
    "playerServer": "https://online.aflam4you.org/playeraf.php?vid=9733"
  },
  {
    "title": "beIN Sports 3 xtra",
    "image": "https://online.aflam4you.org/templates/aflam25555/img/echo-lzld.png",
    "playerServer": "https://online.aflam4you.org/playeraf.php?vid=2910"
  },
  {
    "title": "ثمانية 2",
    "image": "https://online.aflam4you.org/templates/aflam25555/img/echo-lzld.png",
    "playerServer": "https://online.aflam4you.org/playeraf.php?vid=4834"
  },
  {
    "title": "El Haddaf TV",
    "image": "https://online.aflam4you.org/templates/aflam25555/img/echo-lzld.png",
    "playerServer": "https://online.aflam4you.org/playeraf.php?vid=1262"
  },
  {
    "title": "Jordan Sport",
    "image": "https://online.aflam4you.org/templates/aflam25555/img/echo-lzld.png",
    "playerServer": "https://online.aflam4you.org/playeraf.php?vid=7855"
  },
  {
    "title": "Diwan Sport",
    "image": "https://online.aflam4you.org/templates/aflam25555/img/echo-lzld.png",
    "playerServer": "https://online.aflam4you.org/playeraf.php?vid=9294"
  },
  {
    "title": "Sport TV 3",
    "image": "https://online.aflam4you.org/templates/aflam25555/img/echo-lzld.png",
    "playerServer": "https://online.aflam4you.org/playeraf.php?vid=912"
  },
  {
    "title": "الكأس 9",
    "image": "https://online.aflam4you.org/templates/aflam25555/img/echo-lzld.png",
    "playerServer": "https://online.aflam4you.org/playeraf.php?vid=8078"
  },
  {
    "title": "Sport TV 2",
    "image": "https://online.aflam4you.org/templates/aflam25555/img/echo-lzld.png",
    "playerServer": "https://online.aflam4you.org/playeraf.php?vid=4958"
  },
  {
    "title": "Zamalek TV",
    "image": "https://online.aflam4you.org/templates/aflam25555/img/echo-lzld.png",
    "playerServer": "https://online.aflam4you.org/playeraf.php?vid=6100"
  },
  {
    "title": "الكأس 7",
    "image": "https://online.aflam4you.org/templates/aflam25555/img/echo-lzld.png",
    "playerServer": "https://online.aflam4you.org/playeraf.php?vid=6909"
  },
  {
    "title": "ثمانية 3",
    "image": "https://online.aflam4you.org/templates/aflam25555/img/echo-lzld.png",
    "playerServer": "https://online.aflam4you.org/playeraf.php?vid=94"
  },
  {
    "title": "الرياضية 3",
    "image": "https://online.aflam4you.org/templates/aflam25555/img/echo-lzld.png",
    "playerServer": "https://online.aflam4you.org/playeraf.php?vid=9151"
  },
  {
    "title": "الرياضية 2",
    "image": "https://online.aflam4you.org/templates/aflam25555/img/echo-lzld.png",
    "playerServer": "https://online.aflam4you.org/playeraf.php?vid=3383"
  },
  {
    "title": "SSC NEWS Sports",
    "image": "https://online.aflam4you.org/templates/aflam25555/img/echo-lzld.png",
    "playerServer": "https://online.aflam4you.org/playeraf.php?vid=4538"
  },
  {
    "title": "Sport TV 4",
    "image": "https://online.aflam4you.org/templates/aflam25555/img/echo-lzld.png",
    "playerServer": "https://online.aflam4you.org/playeraf.php?vid=5753"
  },
  {
    "title": "الرابعة الرياضية",
    "image": "https://online.aflam4you.org/templates/aflam25555/img/echo-lzld.png",
    "playerServer": "https://online.aflam4you.org/playeraf.php?vid=9610"
  },
  {
    "title": "الكأس 8",
    "image": "https://online.aflam4you.org/templates/aflam25555/img/echo-lzld.png",
    "playerServer": "https://online.aflam4you.org/playeraf.php?vid=9643"
  },
  {
    "title": "الرياضية 4",
    "image": "https://online.aflam4you.org/templates/aflam25555/img/echo-lzld.png",
    "playerServer": "https://online.aflam4you.org/playeraf.php?vid=5839"
  },
  {
    "title": "Dubai Sports 1",
    "image": "https://online.aflam4you.org/templates/aflam25555/img/echo-lzld.png",
    "playerServer": "https://online.aflam4you.org/playeraf.php?vid=1652"
  },
  {
    "title": "Al Sharjah Sports",
    "image": "https://online.aflam4you.org/templates/aflam25555/img/echo-lzld.png",
    "playerServer": "https://online.aflam4you.org/playeraf.php?vid=7346"
  },
  {
    "title": "Oman Sports",
    "image": "https://online.aflam4you.org/templates/aflam25555/img/echo-lzld.png",
    "playerServer": "https://online.aflam4you.org/playeraf.php?vid=6276"
  },
  {
    "title": "الكأس 12",
    "image": "https://online.aflam4you.org/templates/aflam25555/img/echo-lzld.png",
    "playerServer": "https://online.aflam4you.org/playeraf.php?vid=9193"
  },
  {
    "title": "الكأس 10",
    "image": "https://online.aflam4you.org/templates/aflam25555/img/echo-lzld.png",
    "playerServer": "https://online.aflam4you.org/playeraf.php?vid=2387"
  },
  {
    "title": "الكأس 11",
    "image": "https://online.aflam4you.org/templates/aflam25555/img/echo-lzld.png",
    "playerServer": "https://online.aflam4you.org/playeraf.php?vid=4023"
  },
  {
    "title": "Dubai Sports 2",
    "image": "https://online.aflam4you.org/templates/aflam25555/img/echo-lzld.png",
    "playerServer": "https://online.aflam4you.org/playeraf.php?vid=4303"
  },
  {
    "title": "Bahrain Sports 2",
    "image": "https://online.aflam4you.org/templates/aflam25555/img/echo-lzld.png",
    "playerServer": "https://online.aflam4you.org/playeraf.php?vid=9803"
  },
  {
    "title": "Bahrain Sports 1",
    "image": "https://online.aflam4you.org/templates/aflam25555/img/echo-lzld.png",
    "playerServer": "https://online.aflam4you.org/playeraf.php?vid=9722"
  },
  {
    "title": "On Sport Max",
    "image": "https://online.aflam4you.org/templates/aflam25555/img/echo-lzld.png",
    "playerServer": "https://online.aflam4you.org/playeraf.php?vid=3048"
  }
]